MANIFEST.in
README.md
lolly.py
setup.py
lolly.egg-info/PKG-INFO
lolly.egg-info/SOURCES.txt
lolly.egg-info/dependency_links.txt
lolly.egg-info/entry_points.txt
lolly.egg-info/not-zip-safe
lolly.egg-info/requires.txt
lolly.egg-info/top_level.txt
lollyttf/__init__.py
lollyttf/msyh.ttf