Metadata-Version: 1.0
Name: lolly
Version: 0.1.0
Summary: Generate words gif image via the command line
Home-page: https://github.com/chenjiandongx/lolly
Author: chenjiandongx
Author-email: chenjiandongx@qq.com
License: MIT
Platform: UNKNOWN
